bam2cell/GenerateBAM.py
bam2cell/__init__.py
bam2cell/_utils.py
bam2cell-0.2.dist-info/METADATA
bam2cell-0.2.dist-info/WHEEL
bam2cell-0.2.dist-info/licenses/LICENSE
bam2cell-0.2.dist-info/RECORD
