Metadata-Version: 2.4
Name: bam2cell
Version: 0.2
Summary: A method to split BAM files for celltypes
Project-URL: Homepage, https://github.com/davidrm-bio/bam2cell
Author-email: David Rodriguez Morales <rodriguezmorales@med.uni-frankfurt.de>
Maintainer-email: David Rodriguez Morales <rodriguezmorales@med.uni-frankfurt.de>
License: MIT License
License-File: LICENSE
Classifier: Programming Language :: Python :: 3 :: Only
Classifier: Programming Language :: Python :: 3.11
Classifier: Programming Language :: Python :: 3.12
Requires-Python: >=3.10
Requires-Dist: anndata
Requires-Dist: multiprocess
Requires-Dist: numpy
Requires-Dist: pandas
Requires-Dist: pysam
Requires-Dist: scipy
Requires-Dist: tqdm
